MANIFEST.in
setup.cfg
setup.py
django_mce_spellcheck/__init__.py
django_mce_spellcheck/models.py
django_mce_spellcheck/urls.py
django_mce_spellcheck/views.py
django_mce_spellcheck.egg-info/PKG-INFO
django_mce_spellcheck.egg-info/SOURCES.txt
django_mce_spellcheck.egg-info/dependency_links.txt
django_mce_spellcheck.egg-info/not-zip-safe
django_mce_spellcheck.egg-info/requires.txt
django_mce_spellcheck.egg-info/top_level.txt
django_mce_spellcheck/static/grapelli/tinymce/jscripts/tiny_mce/plugins/spellchecker/editor_plugin.js
django_mce_spellcheck/static/grapelli/tinymce/jscripts/tiny_mce/plugins/spellchecker/editor_plugin_src.js
django_mce_spellcheck/static/grapelli/tinymce/jscripts/tiny_mce/plugins/spellchecker/css/content.css
django_mce_spellcheck/static/js/spellcheck_fix.js