Metadata-Version: 1.1
Name: django_mce_spellcheck
Version: 0.1.2
Summary: Django app that provides a backend for the tinymce spellcheck plugin. Particularly useful for Mezzanine
Home-page: https://github.com/seanodonnell/django_mce_spellcheck
Author: Sean O'Donnell
Author-email: sean@odonnell.nu
License: UNKNOWN
Download-URL: https://github.com/seanodonnell/django_mce_spellcheck/archive/master.zip
Keywords: django,tinymce,spellcheck,mezzanine
Platform: UNKNOWN
Classifier: Programming Language :: Python
Classifier: Development Status :: 4 - Beta
Classifier: Environment :: Plugins
Classifier: Framework :: Django
Classifier: Intended Audience :: Developers
Classifier: License :: OSI Approved :: GNU Lesser General Public License v2 (LGPLv2)
